phytclust/__init__.py
phytclust/__main__.py
phytclust/phytclust_logo_colour.png
phytclust/phytclust_logo_colour_text_only.png
phytclust/small_logo.png
phytclust/validation.py
phytclust/algo/__init__.py
phytclust/algo/bins.py
phytclust/algo/bootstrap_stability.py
phytclust/algo/core.py
phytclust/algo/dp.py
phytclust/algo/scoring.py
phytclust/cli/__init__.py
phytclust/cli/__main__.py
phytclust/cli/_cli.py
phytclust/cli/ascii_logo.txt
phytclust/io/__init__.py
phytclust/io/save_results.py
phytclust/metrics/__init__.py
phytclust/metrics/indices.py
phytclust/selection/__init__.py
phytclust/selection/pd_representatives.py
phytclust/utils/__init__.py
phytclust/utils/tree.py
phytclust/viz/__init__.py
phytclust/viz/cluster_plot.py
phytclust/viz/plotting.py
phytclust/viz/scores_plot.py
phytclust-0.1.1.dist-info/licenses/LICENSE
phytclust-0.1.1.dist-info/METADATA
phytclust-0.1.1.dist-info/WHEEL
phytclust-0.1.1.dist-info/entry_points.txt
phytclust-0.1.1.dist-info/top_level.txt
phytclust-0.1.1.dist-info/RECORD
