Metadata-Version: 2.4
Name: phytclust
Version: 0.1.1
Summary: PhytClust takes a phylogenetic tree as input and outputs monophyletic leaf clusters that best fit the tree structure.
Author-email: Katyayni Ganesan <katyayni.ganesan@iccb-cologne.org>, Roland F Schwarz <roland.schwarz@iccb-cologne.org>
Maintainer-email: Katyayni Ganesan <katyayni.ganesan@iccb-cologne.org>
License:                     GNU GENERAL PUBLIC LICENSE
Project-URL: Documentation, https://bitbucket.org/schwarzlab/phytclust
Project-URL: Source, https://bitbucket.org/schwarzlab/phytclust
Project-URL: Tracker, https://bitbucket.org/schwarzlab/phytclust/issues
Keywords: phylogenetics,clustering,taxonomy,classification,dynamic programming
Classifier: Development Status :: 4 - Beta
Classifier: Intended Audience :: Science/Research
Classifier: Programming Language :: Python :: 3.9
Classifier: License :: OSI Approved :: GNU General Public License v3 (GPLv3)
Requires-Python: >=3.9
License-File: LICENSE
Requires-Dist: numpy>=1.24
Requires-Dist: biopython>=1.85
Requires-Dist: matplotlib>=3.7
Requires-Dist: pandas>=2.0
Requires-Dist: scipy>=1.10
Requires-Dist: PyYAML>=6.0
Requires-Dist: rich>=13.0
Provides-Extra: dev
Requires-Dist: pytest>=7.0; extra == "dev"
Requires-Dist: pytest-cov>=4.0; extra == "dev"
Requires-Dist: black>=24.0; extra == "dev"
Requires-Dist: ruff>=0.5; extra == "dev"
Requires-Dist: mypy>=1.10; extra == "dev"
Requires-Dist: pre-commit>=3.0; extra == "dev"
Dynamic: license-file
